[
    {
        "id": 1,
        "nev": "Vásáry Izabella",
        "img": "img/fodrasz-5.jpg",
        "pozicio": "mesterfodrász és hajápolási szakértő",
        "nyitvatartas": [
            {
                "nap": "Hétfő",
                "napIndex": 1,
                "tol": "10:00",
                "ig": "18:00"
            },
            {
                "nap": "Kedd",
                "napIndex": 2,
                "tol": "8:00",
                "ig": "14:00"
            },
            {
                "nap": "Szerda",
                "napIndex": 3,
                "tol": "10:00",
                "ig": "18:00"
            },
            {
                "nap": "Péntek",
                "napIndex": 5,
                "tol": "10:00",
                "ig": "20:00"
            },
            {
                "nap": "Szombat",
                "napIndex": 6,
                "tol": "8:00",
                "ig": "12:00"
            }
        ],
        "szolgaltatasok": [
            {
                "nev": "női hajvágás",
                "idotartam": "30 perc"
            },
            {
                "nev": "férfi hajvágás",
                "idotartam": "20 perc"
            },
            {
                "nev": "gyermek hajvágás",
                "idotartam": "15 perc"
            },
            {
                "nev": "hajkezelés: keratin",
                "idotartam": "180 perc"
            },
            {
                "nev": "hajkezelés: repair iron",
                "idotartam": "130 perc"
            },
            {
                "nev": "hajfestés: ombre",
                "idotartam": "120 perc"
            },
            {
                "nev": "hajfestés: teli",
                "idotartam": "120 perc"
            },
            {
                "nev": "hajfestés: balayage",
                "idotartam": "120 perc"
            },
            {
                "nev": "hajfestés: babylights",
                "idotartam": "120 perc"
            },
            {
                "nev": "konzultáció",
                "idotartam": "10 perc"
            }
        ],
        "idopontok": [
            {
                "datum": "2023.09.01",
                "ora": "10:00"
            },
            {
                "datum": "2023.09.02",
                "ora": "14:00"
            },
            {
                "datum": "2023.09.03",
                "ora": "11:00"
            }
        ],
        "foglalas": [
            {
                "vendegNev": "Kovács Csilla",
                "datum": "2023.08.23",
                "ora": "10:00"
            },
            {
                "vendegNev": "Nagy Gertrúd",
                "datum": "2023.08.23",
                "ora": "14:00"
            }
        ]
    },
    {
        "id": 2,
        "nev": "Mester Manó",
        "img": "img/fodrasz-1.jpg",
        "pozicio": "mesterfodrász és borbély",
        "nyitvatartas": [
            {
                "nap": "Hétfő",
                "napIndex": 1,
                "tol": "9:00",
                "ig": "17:00"
            },
            {
                "nap": "Kedd",
                "napIndex": 2,
                "tol": "9:00",
                "ig": "17:00"
            },
            {
                "nap": "Szerda",
                "napIndex": 3,
                "tol": "9:00",
                "ig": "17:00"
            },
            {
                "nap": "Csütörtök",
                "napIndex": 4,
                "tol": "9:00",
                "ig": "17:00"
            },
            {
                "nap": "Péntek",
                "napIndex": 5,
                "tol": "9:00",
                "ig": "17:00"
            }
        ],
        "szolgaltatasok": [
            {
                "nev": "női hajvágás",
                "idotartam": "30 perc"
            },
            {
                "nev": "férfi hajvágás",
                "idotartam": "20 perc"
            },
            {
                "nev": "hajkezelés: keratin",
                "idotartam": "180 perc"
            },
            {
                "nev": "hajkezelés: repair iron",
                "idotartam": "130 perc"
            },
            {
                "nev": "hajfestés: balayage",
                "idotartam": "120 perc"
            },
            {
                "nev": "hajfestés: babylights",
                "idotartam": "120 perc"
            },
            {
                "nev": "borbély: bajusz",
                "idotartam": "20 perc"
            },
            {
                "nev": "borbély: szakáll",
                "idotartam": "30 perc"
            },
            {
                "nev": "borbély: full face",
                "idotartam": "100 perc"
            },
            {
                "nev": "konzultáció",
                "idotartam": "10 perc"
            }
        ],
        "idopontok": [
            {
                "datum": "2023.09.01",
                "ora": "9:30"
            },
            {
                "datum": "2023.09.01",
                "ora": "10:00"
            },
            {
                "datum": "2023.09.01",
                "ora": "10:30"
            },
            {
                "datum": "2023.09.02",
                "ora": "9:30"
            },
            {
                "datum": "2023.09.02",
                "ora": "10:00"
            },
            {
                "datum": "2023.09.02",
                "ora": "10:30"
            },
            {
                "datum": "2023.09.03",
                "ora": "9:30"
            },
            {
                "datum": "2023.09.03",
                "ora": "10:00"
            },
            {
                "datum": "2023.09.03",
                "ora": "10:30"
            },
            {
                "datum": "2023.09.04",
                "ora": "9:30"
            },
            {
                "datum": "2023.09.04",
                "ora": "10:00"
            }
        ],
        "foglalas": [
            {
                "vendegNev": "Kis Anna",
                "datum": "2023.08.25",
                "ora": "15:00"
            },
            {
                "vendegNev": "Németh Béla",
                "datum": "2023.08.26",
                "ora": "12:00"
            }
        ]
    },
    {
        "id": 3,
        "nev": "Hegyi Henrietta",
        "img": "img/fodrasz-3.jpg",
        "pozicio": "női fodrász és színszakértő",
        "nyitvatartas": [
            {
                "nap": "Hétfő",
                "napIndex": 1,
                "tol": "12:00",
                "ig": "20:00"
            },
            {
                "nap": "Szerda",
                "napIndex": 3,
                "tol": "12:00",
                "ig": "20:00"
            },
            {
                "nap": "Péntek",
                "napIndex": 5,
                "tol": "12:00",
                "ig": "20:00"
            }
        ],
        "szolgaltatasok": [
            {
                "nev": "női hajvágás",
                "idotartam": "30 perc"
            },
            {
                "nev": "férfi hajvágás",
                "idotartam": "20 perc"
            },
            {
                "nev": "hajfestés: ombre",
                "idotartam": "120 perc"
            },
            {
                "nev": "hajfestés: teli",
                "idotartam": "120 perc"
            },
            {
                "nev": "hajfestés: balayage",
                "idotartam": "120 perc"
            },
            {
                "nev": "hajfestés: melírozás",
                "idotartam": "120 perc"
            },
            {
                "nev": "hajfestés: babylights",
                "idotartam": "120 perc"
            },
            {
                "nev": "konzultáció",
                "idotartam": "10 perc"
            }
        ],
        "idopontok": [
            {
                "datum": "2023.09.05",
                "ora": "12:30"
            },
            {
                "datum": "2023.09.05",
                "ora": "14:00"
            },
            {
                "datum": "2023.09.05",
                "ora": "15:30"
            },
            {
                "datum": "2023.09.06",
                "ora": "12:30"
            },
            {
                "datum": "2023.09.06",
                "ora": "14:00"
            },
            {
                "datum": "2023.09.06",
                "ora": "15:30"
            },
            {
                "datum": "2023.09.07",
                "ora": "12:30"
            },
            {
                "datum": "2023.09.07",
                "ora": "14:00"
            },
            {
                "datum": "2023.09.07",
                "ora": "15:30"
            },
            {
                "datum": "2023.09.08",
                "ora": "12:30"
            },
            {
                "datum": "2023.09.08",
                "ora": "14:00"
            }
        ],
        "foglalas": [
            {
                "vendegNev": "Tóth Gábor",
                "datum": "2023.09.01",
                "ora": "18:00"
            },
            {
                "vendegNev": "Kovácsné Eszter",
                "datum": "2023.09.03",
                "ora": "15:30"
            }
        ]
    },
    {
        "id": 4,
        "nev": "Vígh Szandra",
        "img": "img/fodrasz-4.jpg",
        "pozicio": "mesterfodrász és alkalmi haj specialista",
        "nyitvatartas": [
            {
                "nap": "Hétfő",
                "napIndex": 1,
                "tol": "11:00",
                "ig": "19:00"
            },
            {
                "nap": "Szerda",
                "napIndex": 3,
                "tol": "11:00",
                "ig": "19:00"
            },
            {
                "nap": "Péntek",
                "napIndex": 5,
                "tol": "11:00",
                "ig": "19:00"
            },
            {
                "nap": "Szombat",
                "napIndex": 6,
                "tol": "10:00",
                "ig": "14:00"
            }
        ],
        "szolgaltatasok": [
            {
                "nev": "női hajvágás",
                "idotartam": "30 perc"
            },
            {
                "nev": "férfi hajvágás",
                "idotartam": "20 perc"
            },
            {
                "nev": "hajkezelés: keratin",
                "idotartam": "180 perc"
            },
            {
                "nev": "hajkezelés: repair iron",
                "idotartam": "130 perc"
            },
            {
                "nev": "hajfestés: ombre",
                "idotartam": "120 perc"
            },
            {
                "nev": "hajfestés: teli",
                "idotartam": "120 perc"
            },
            {
                "nev": "hajfestés: balayage",
                "idotartam": "120 perc"
            },
            {
                "nev": "alkalmi haj:szalgavató",
                "idotartam": "180 perc"
            },
            {
                "nev": "alkalmi haj:esküvő",
                "idotartam": "220 perc"
            },
            {
                "nev": "konzultáció",
                "idotartam": "10 perc"
            }
        ],
        "idopontok": [
            {
                "datum": "2023.09.09",
                "ora": "11:30"
            },
            {
                "datum": "2023.09.09",
                "ora": "13:00"
            },
            {
                "datum": "2023.09.09",
                "ora": "14:30"
            },
            {
                "datum": "2023.09.10",
                "ora": "11:30"
            },
            {
                "datum": "2023.09.10",
                "ora": "13:00"
            },
            {
                "datum": "2023.09.10",
                "ora": "14:30"
            },
            {
                "datum": "2023.09.11",
                "ora": "11:30"
            },
            {
                "datum": "2023.09.11",
                "ora": "13:00"
            },
            {
                "datum": "2023.09.11",
                "ora": "14:30"
            },
            {
                "datum": "2023.09.12",
                "ora": "11:30"
            },
            {
                "datum": "2023.09.12",
                "ora": "13:00"
            }
        ],
        "foglalas": [
            {
                "vendegNev": "Horváth Péter",
                "datum": "2023.09.10",
                "ora": "14:00"
            },
            {
                "vendegNev": "Kiss Virág",
                "datum": "2023.09.10",
                "ora": "16:00"
            }
        ]
    },
    {
        "id": 5,
        "nev": "Petris Hanna",
        "img": "img/fodrasz-2.jpg",
        "pozicio": "női és gyermek fodrász",
        "nyitvatartas": [
            {
                "nap": "Kedd",
                "napIndex": 2,
                "tol": "10:00",
                "ig": "18:00"
            },
            {
                "nap": "Csütörtök",
                "napIndex": 4,
                "tol": "10:00",
                "ig": "18:00"
            },
            {
                "nap": "Szombat",
                "napIndex": 6,
                "tol": "8:00",
                "ig": "14:00"
            }
        ],
        "szolgaltatasok": [
            {
                "nev": "női hajvágás",
                "idotartam": "30 perc"
            },
            {
                "nev": "gyermek hajvágás",
                "idotartam": "15 perc"
            },
            {
                "nev": "hajkezelés: keratin",
                "idotartam": "180 perc"
            },
            {
                "nev": "hajkezelés: repair iron",
                "idotartam": "130 perc"
            },
            {
                "nev": "hajfestés: teli",
                "idotartam": "120 perc"
            },
            {
                "nev": "hajfestés: melírozás",
                "idotartam": "120 perc"
            },
            {
                "nev": "konzultáció",
                "idotartam": "10 perc"
            }
        ],
        "idopontok": [
            {
                "datum": "2023.09.13",
                "ora": "10:00"
            },
            {
                "datum": "2023.09.13",
                "ora": "11:00"
            },
            {
                "datum": "2023.09.13",
                "ora": "12:00"
            },
            {
                "datum": "2023.09.15",
                "ora": "10:00"
            },
            {
                "datum": "2023.09.15",
                "ora": "11:00"
            },
            {
                "datum": "2023.09.15",
                "ora": "12:00"
            },
            {
                "datum": "2023.09.16",
                "ora": "10:00"
            },
            {
                "datum": "2023.09.16",
                "ora": "11:00"
            },
            {
                "datum": "2023.09.16",
                "ora": "12:00"
            },
            {
                "datum": "2023.09.17",
                "ora": "10:00"
            },
            {
                "datum": "2023.09.17",
                "ora": "11:00"
            }
        ],
        "foglalas": [
            {
                "vendegNev": "Szabó Mária",
                "datum": "2023.08.31",
                "ora": "11:30"
            },
            {
                "vendegNev": "Király Levente",
                "datum": "2023.09.02",
                "ora": "13:00"
            }
        ]
    }
]
